{"predictions": {"video25": [{"image_id": "video25", "caption": "a person playing a video game and commentating"}], "video109": [{"image_id": "video109", "caption": "a dark haired man is talking about a movie"}], "video63": [{"image_id": "video63", "caption": "a cartoon of a man and a man in a suit"}], "video78": [{"image_id": "video78", "caption": "a woman in a blue shirt is walking on a field"}], "video81": [{"image_id": "video81", "caption": "a fire is burning"}], "video48": [{"image_id": "video48", "caption": "a group of people are having a conversation in a large building"}], "video118": [{"image_id": "video118", "caption": "a man is playing a guitar while another man is playing in the background"}], "video99": [{"image_id": "video99", "caption": "a large group of people are watching a man"}], "video127": [{"image_id": "video127", "caption": "a man is standing in a dark room with a black shirt and playing with a black and white"}], "video5": [{"image_id": "video5", "caption": "a man is walking"}], "video34": [{"image_id": "video34", "caption": "a man is talking on the tv show"}], "video120": [{"image_id": "video120", "caption": "a video game is being played"}], "video35": [{"image_id": "video35", "caption": "a man is standing in the water"}], "video95": [{"image_id": "video95", "caption": "a man is talking to a man in a room"}], "video47": [{"image_id": "video47", "caption": "a man is talking about a movie"}], "video11": [{"image_id": "video11", "caption": "a man is swimming"}], "video60": [{"image_id": "video60", "caption": "a girl is talking with a man in a black dress"}], "video115": [{"image_id": "video115", "caption": "there is a woman is talking with a man"}], "video32": [{"image_id": "video32", "caption": "a woman is talking about the movie"}], "video38": [{"image_id": "video38", "caption": "a man is diving in the water"}], "video3": [{"image_id": "video3", "caption": "a man and woman laying in bed"}], "video26": [{"image_id": "video26", "caption": "a man is talking about a video game"}], "video79": [{"image_id": "video79", "caption": "a man is walking through a forest"}], "video126": [{"image_id": "video126", "caption": "a woman is talking to a man in a black suit"}], "video13": [{"image_id": "video13", "caption": "a beautiful scene of water and the water"}], "video72": [{"image_id": "video72", "caption": "a man is singing and dancing"}], "video85": [{"image_id": "video85", "caption": "a man is standing in a building and looking at a building"}], "video112": [{"image_id": "video112", "caption": "a person is talking about the universe and the universe"}], "video21": [{"image_id": "video21", "caption": "a woman is talking"}], "video76": [{"image_id": "video76", "caption": "a person is playing a video game"}], "video42": [{"image_id": "video42", "caption": "a man is sitting in a room with a gun"}], "video58": [{"image_id": "video58", "caption": "a woman in a green dress is talking to a man"}], "video61": [{"image_id": "video61", "caption": "a man is standing in a forest with a large animal"}], "video75": [{"image_id": "video75", "caption": "a woman is shooting a man in a cave"}], "video12": [{"image_id": "video12", "caption": "a person is showing some thing on the screen"}], "video19": [{"image_id": "video19", "caption": "a man is dancing"}], "video89": [{"image_id": "video89", "caption": "a person is playing a video game"}], "video102": [{"image_id": "video102", "caption": "a man in a black jacket is standing by a man"}], "video107": [{"image_id": "video107", "caption": "a man is fighting with a man"}], "video17": [{"image_id": "video17", "caption": "a man is driving a car in a video game"}], "video117": [{"image_id": "video117", "caption": "a man is standing"}], "video71": [{"image_id": "video71", "caption": "a man is shooting a gun"}], "video27": [{"image_id": "video27", "caption": "a man is fighting a game"}], "video83": [{"image_id": "video83", "caption": "a girl is playing with a boy"}], "video45": [{"image_id": "video45", "caption": "a man is talking about a large building"}], "video103": [{"image_id": "video103", "caption": "a man is standing in a video game and talking"}], "video41": [{"image_id": "video41", "caption": "a video of a movie"}], "video10": [{"image_id": "video10", "caption": "a man is talking about the <UNK> of the universe"}], "video128": [{"image_id": "video128", "caption": "a man is talking"}], "video74": [{"image_id": "video74", "caption": "a woman with blonde hair is talking to a man"}], "video50": [{"image_id": "video50", "caption": "a man in a suit is talking to a woman"}], "video119": [{"image_id": "video119", "caption": "a video game is being played"}], "video106": [{"image_id": "video106", "caption": "a man is walking through a room"}], "video94": [{"image_id": "video94", "caption": "a woman is sitting in the chair and talking"}], "video1": [{"image_id": "video1", "caption": "a person is showing something"}], "video15": [{"image_id": "video15", "caption": "a woman is talking about a lake"}], "video56": [{"image_id": "video56", "caption": "a woman is talking to a man"}], "video125": [{"image_id": "video125", "caption": "a man is talking about his movie"}], "video129": [{"image_id": "video129", "caption": "a man is talking about something in a movie"}], "video57": [{"image_id": "video57", "caption": "a woman with long hair is talking to a man"}], "video24": [{"image_id": "video24", "caption": "a person is explaining something"}], "video59": [{"image_id": "video59", "caption": "a woman is talking to a man"}], "video33": [{"image_id": "video33", "caption": "a man is talking about the universe"}], "video4": [{"image_id": "video4", "caption": "a girl is laying down and talking"}], "video67": [{"image_id": "video67", "caption": "a man is talking"}], "video114": [{"image_id": "video114", "caption": "a man is talking to a woman"}], "video43": [{"image_id": "video43", "caption": "a man is talking"}], "video111": [{"image_id": "video111", "caption": "a video of a rock star wars video"}], "video54": [{"image_id": "video54", "caption": "a woman is talking to a man in a movie"}], "video121": [{"image_id": "video121", "caption": "a video game is being played"}], "video14": [{"image_id": "video14", "caption": "a movie scene is going in to the camera"}], "video52": [{"image_id": "video52", "caption": "a woman is talking"}], "video65": [{"image_id": "video65", "caption": "a man is talking to another man"}], "video82": [{"image_id": "video82", "caption": "a man is dressed as a woman"}], "video86": [{"image_id": "video86", "caption": "a man is flying with a tree and it is an animated man is talking about a <UNK>"}], "video124": [{"image_id": "video124", "caption": "a video game character is firing a gun"}], "video100": [{"image_id": "video100", "caption": "a woman is talking to a man"}], "video93": [{"image_id": "video93", "caption": "a man is talking to a woman"}], "video51": [{"image_id": "video51", "caption": "a woman is talking about the movie the hero is being shown"}], "video92": [{"image_id": "video92", "caption": "a man is talking to a woman"}], "video40": [{"image_id": "video40", "caption": "a man is talking"}], "video55": [{"image_id": "video55", "caption": "a woman is talking to a man"}], "video16": [{"image_id": "video16", "caption": "a flying plane is flying over the ocean"}], "video8": [{"image_id": "video8", "caption": "a man with a black suit is talking to a man in a blue shirt"}], "video7": [{"image_id": "video7", "caption": "a ship is on the sea shore"}], "video87": [{"image_id": "video87", "caption": "a man is running and jumping from a building"}], "video123": [{"image_id": "video123", "caption": "a video game is being played"}], "video97": [{"image_id": "video97", "caption": "a video game character is talking"}], "video37": [{"image_id": "video37", "caption": "a person is playing a video game"}], "video28": [{"image_id": "video28", "caption": "a woman is talking to a man"}], "video31": [{"image_id": "video31", "caption": "a scene from the movie the avengers"}], "video101": [{"image_id": "video101", "caption": "a man and a woman are singing in a music video"}], "video18": [{"image_id": "video18", "caption": "a man is talking about a video game"}], "video73": [{"image_id": "video73", "caption": "a man is shooting a gun"}], "video91": [{"image_id": "video91", "caption": "a man is talking about the movie"}], "video2": [{"image_id": "video2", "caption": "a man is talking about the <UNK> of a machine"}], "video90": [{"image_id": "video90", "caption": "a man is looking at a building in the city"}], "video110": [{"image_id": "video110", "caption": "a man is shooting a gun and another man is talking about it"}], "video98": [{"image_id": "video98", "caption": "a man is talking while another man is playing a video game"}], "video36": [{"image_id": "video36", "caption": "a man is talking while a woman is talking"}], "video122": [{"image_id": "video122", "caption": "a large group of people are sitting at a stadium"}], "video22": [{"image_id": "video22", "caption": "a girl is wearing a black dress and a black dress"}], "video46": [{"image_id": "video46", "caption": "a man is standing in the snow and talking"}], "video44": [{"image_id": "video44", "caption": "a man is playing a video game"}], "video23": [{"image_id": "video23", "caption": "a woman is using a cigarette to a man"}], "video113": [{"image_id": "video113", "caption": "a man is talking about the <UNK> of the <UNK>"}], "video62": [{"image_id": "video62", "caption": "a video of a man drawing on the ocean"}], "video69": [{"image_id": "video69", "caption": "a man in a blue suit is singing a song"}], "video9": [{"image_id": "video9", "caption": "two men are talking"}], "video105": [{"image_id": "video105", "caption": "a man is singing a song and dancing"}], "video64": [{"image_id": "video64", "caption": "a large group of people are swimming around in a large land"}], "video29": [{"image_id": "video29", "caption": "a woman is talking about a video game"}], "video30": [{"image_id": "video30", "caption": "a woman is talking to a man"}], "video53": [{"image_id": "video53", "caption": "a woman is talking about a man"}], "video116": [{"image_id": "video116", "caption": "a man is flying around in the sky"}], "video39": [{"image_id": "video39", "caption": "a man is talking about the universe"}], "video84": [{"image_id": "video84", "caption": "a man is running"}], "video88": [{"image_id": "video88", "caption": "a man is playing a video game and talking about it"}], "video96": [{"image_id": "video96", "caption": "a man is talking"}], "video49": [{"image_id": "video49", "caption": "a video game is being played"}], "video68": [{"image_id": "video68", "caption": "a man is playing a video game"}], "video70": [{"image_id": "video70", "caption": "a man is walking down the street"}], "video80": [{"image_id": "video80", "caption": "a man is walking"}], "video108": [{"image_id": "video108", "caption": "a woman is talking to a man"}], "video104": [{"image_id": "video104", "caption": "a man is playing a video game"}], "video66": [{"image_id": "video66", "caption": "a man is singing a song"}], "video6": [{"image_id": "video6", "caption": "a man is standing in the water"}], "video20": [{"image_id": "video20", "caption": "a man is playing a video game"}], "video77": [{"image_id": "video77", "caption": "a woman is sitting"}]}}